[
  {
    "bill_id": 1,
    "bill_code": "H.R.1234",
    "official_title": "Affordable Care Act Expansion and Improvement Act of 2024",
    "simple_summary": "Expands healthcare coverage under the Affordable Care Act, lowers prescription drug costs, and increases subsidies for low-income families.",
    "full_text_url": "https://www.congress.gov/bill/118th-congress/house-bill/1234",
    "status": "Passed House",
    "congress_session": 118,
    "introduced_date": "2024-02-01",
    "vote_date": "2024-03-15",
    "vote_result_yes": 220,
    "vote_result_no": 210,
    "vote_result_present": 3,
    "vote_result_absent": 2
  },
  {
    "bill_id": 2,
    "bill_code": "H.R.5678",
    "official_title": "Climate Action Now Act",
    "simple_summary": "Requires the United States to meet its nationally determined contribution under the Paris Climate Agreement and establishes a Green Climate Fund.",
    "full_text_url": "https://www.congress.gov/bill/118th-congress/house-bill/5678",
    "status": "In Committee",
    "congress_session": 118,
    "introduced_date": "2024-04-10",
    "vote_date": "2024-05-22",
    "vote_result_yes": 225,
    "vote_result_no": 205,
    "vote_result_present": 2,
    "vote_result_absent": 3
  },
  {
    "bill_id": 3,
    "bill_code": "H.R.9012",
    "official_title": "Tax Reform and Simplification Act of 2024",
    "simple_summary": "Reforms the federal tax code by reducing corporate tax rates, simplifying individual tax brackets, and eliminating certain deductions.",
    "full_text_url": "https://www.congress.gov/bill/118th-congress/house-bill/9012",
    "status": "Passed House",
    "congress_session": 118,
    "introduced_date": "2024-06-01",
    "vote_date": "2024-07-10",
    "vote_result_yes": 215,
    "vote_result_no": 218,
    "vote_result_present": 1,
    "vote_result_absent": 1
  },
  {
    "bill_id": 4,
    "bill_code": "H.R.2345",
    "official_title": "Green New Deal Resolution",
    "simple_summary": "Resolution recognizing the duty of the Federal Government to create a Green New Deal to achieve net-zero greenhouse gas emissions through a fair and just transition.",
    "full_text_url": "https://www.congress.gov/bill/118th-congress/house-bill/2345",
    "status": "Introduced",
    "congress_session": 118,
    "introduced_date": "2024-01-15",
    "vote_date": "2024-02-28",
    "vote_result_yes": 195,
    "vote_result_no": 235,
    "vote_result_present": 5,
    "vote_result_absent": 0
  },
  {
    "bill_id": 5,
    "bill_code": "H.R.6789",
    "official_title": "Medicare for All Act of 2024",
    "simple_summary": "Establishes a national health insurance program to provide all individuals residing in the United States with free health care services.",
    "full_text_url": "https://www.congress.gov/bill/118th-congress/house-bill/6789",
    "status": "In Committee",
    "congress_session": 118,
    "introduced_date": "2024-03-01",
    "vote_date": "2024-04-12",
    "vote_result_yes": 180,
    "vote_result_no": 250,
    "vote_result_present": 3,
    "vote_result_absent": 2
  },
  {
    "bill_id": 6,
    "bill_code": "H.R.3456",
    "official_title": "National Defense Authorization Act for Fiscal Year 2024",
    "simple_summary": "Authorizes appropriations for the Department of Defense and increases military spending by 5% to strengthen national security.",
    "full_text_url": "https://www.congress.gov/bill/118th-congress/house-bill/3456",
    "status": "Enacted",
    "congress_session": 118,
    "introduced_date": "2024-05-01",
    "vote_date": "2024-06-05",
    "vote_result_yes": 280,
    "vote_result_no": 150,
    "vote_result_present": 4,
    "vote_result_absent": 1
  },
  {
    "bill_id": 7,
    "bill_code": "H.R.4567",
    "official_title": "Border Security Enhancement Act of 2024",
    "simple_summary": "Provides funding for enhanced border security measures including physical barriers, technology, and additional Border Patrol agents.",
    "full_text_url": "https://www.congress.gov/bill/118th-congress/house-bill/4567",
    "status": "Passed House",
    "congress_session": 118,
    "introduced_date": "2023-12-10",
    "vote_date": "2024-01-20",
    "vote_result_yes": 230,
    "vote_result_no": 200,
    "vote_result_present": 3,
    "vote_result_absent": 2
  },
  {
    "bill_id": 8,
    "bill_code": "H.R.7890",
    "official_title": "Federal Budget Reduction and Deficit Control Act",
    "simple_summary": "Implements mandatory spending cuts across federal agencies to reduce the national deficit over a 10-year period.",
    "full_text_url": "https://www.congress.gov/bill/118th-congress/house-bill/7890",
    "status": "In Committee",
    "congress_session": 118,
    "introduced_date": "2024-02-15",
    "vote_date": "2024-03-30",
    "vote_result_yes": 210,
    "vote_result_no": 220,
    "vote_result_present": 3,
    "vote_result_absent": 2
  },
  {
    "bill_id": 9,
    "bill_code": "H.R.2468",
    "official_title": "Infrastructure Investment and Jobs Act",
    "simple_summary": "Authorizes $1.2 trillion in federal spending for roads, bridges, broadband internet, clean water, and public transit infrastructure.",
    "full_text_url": "https://www.congress.gov/bill/118th-congress/house-bill/2468",
    "status": "Enacted",
    "congress_session": 118,
    "introduced_date": "2024-04-05",
    "vote_date": "2024-05-15",
    "vote_result_yes": 240,
    "vote_result_no": 190,
    "vote_result_present": 3,
    "vote_result_absent": 2
  }
]
